practicejapanese/__init__.py
practicejapanese/main.py
practicejapanese/core/__init__.py
practicejapanese/core/dev_mode.py
practicejapanese/core/kanji.py
practicejapanese/core/quiz_runner.py
practicejapanese/core/utils.py
practicejapanese/core/vocab.py
practicejapanese/data/Kanji.csv
practicejapanese/data/Vocab.csv
practicejapanese/public/__init__.py
practicejapanese/quizzes/__init__.py
practicejapanese/quizzes/audio_quiz.py
practicejapanese/quizzes/filling_quiz.py
practicejapanese/quizzes/kanji_quiz.py
practicejapanese/quizzes/vocab_quiz.py
pjapp-0.7.15.dist-info/METADATA
pjapp-0.7.15.dist-info/WHEEL
pjapp-0.7.15.dist-info/entry_points.txt
pjapp-0.7.15.dist-info/top_level.txt
pjapp-0.7.15.dist-info/RECORD
