Metadata-Version: 2.4
Name: pjapp
Version: 0.7.15
Requires-Dist: requests
Requires-Dist: gtts
Dynamic: requires-dist
